quantify/__init__.py
quantify/compilation.py
quantify/enums.py
quantify/gettables.py
quantify/gettables_profiled.py
quantify/json_utils.py
quantify/math.py
quantify/pulse_compensation.py
quantify/py.typed
quantify/resources.py
quantify/waveforms.py
quantify/yaml_utils.py
quantify/analysis/__init__.py
quantify/analysis/base_analysis.py
quantify/analysis/calibration.py
quantify/analysis/conditional_oscillation_analysis.py
quantify/analysis/cosine_analysis.py
quantify/analysis/fitting_models.py
quantify/analysis/interpolation_analysis.py
quantify/analysis/optimization_analysis.py
quantify/analysis/readout_calibration_analysis.py
quantify/analysis/single_qubit_timedomain.py
quantify/analysis/spectroscopy_analysis.py
quantify/analysis/time_of_flight_analysis.py
quantify/analysis/types.py
quantify/analysis/schemas/AnalysisSettings.json
quantify/analysis/schemas/__init__.py
quantify/backends/__init__.py
quantify/backends/circuit_to_device.py
quantify/backends/corrections.py
quantify/backends/graph_compilation.py
quantify/backends/mock/__init__.py
quantify/backends/mock/mock_rom.py
quantify/backends/types/__init__.py
quantify/backends/types/common.py
quantify/data/__init__.py
quantify/data/dataset_adapters.py
quantify/data/dataset_attrs.py
quantify/data/experiment.py
quantify/data/handling.py
quantify/data/types.py
quantify/device_under_test/__init__.py
quantify/device_under_test/composite_square_edge.py
quantify/device_under_test/device_element.py
quantify/device_under_test/edge.py
quantify/device_under_test/hardware_config.py
quantify/device_under_test/mock_setup.py
quantify/device_under_test/nv_element.py
quantify/device_under_test/quantum_device.py
quantify/device_under_test/spin_edge.py
quantify/device_under_test/spin_element.py
quantify/device_under_test/transmon_element.py
quantify/helpers/__init__.py
quantify/helpers/collections.py
quantify/helpers/diagnostics_report.py
quantify/helpers/generate_acq_channels_data.py
quantify/helpers/importers.py
quantify-0.0.9.dist-info/licenses/LICENSE
quantify-0.0.9.dist-info/METADATA
quantify-0.0.9.dist-info/WHEEL
quantify-0.0.9.dist-info/top_level.txt
quantify-0.0.9.dist-info/RECORD
